[
  {
    "Id": "272959",
    "ThreadId": "79705",
    "Html": "<p>I am having a problem with this piece of code. I can call the GetConnectionRawData method from unmanaged code (Powerbuilder), but when I try to reference the properties of ConnectionData I get errors. But If I get rid of &quot;[ClassInterface(ClassInterfaceType.None)]&quot; I have no problem accessing the properties of ConnectionData. Is there a dll conflict? Are the attributes used properly?&nbsp;Any help will be greatly appreciated.</p>\r\n<p>&nbsp;&nbsp;&nbsp; [ComVisible(true)]<br>&nbsp;&nbsp;&nbsp; [ClassInterface(ClassInterfaceType.None)]<br>&nbsp;&nbsp;&nbsp; [Guid(&quot;1B09A9E8-480F-4b4b-95F5-2CD6586B44A7&quot;)]<br>&nbsp;&nbsp;&nbsp; public class DBConfigProxyFacade : IDBConfigProxy, IDisposable<br>&nbsp;&nbsp;&nbsp; {</p>\r\n<p>&nbsp;&nbsp;&nbsp;&nbsp;&nbsp;&nbsp;&nbsp; [ComVisible(true)]<br>&nbsp;&nbsp;&nbsp;&nbsp;&nbsp;&nbsp;&nbsp; [return: MarshalAs(UnmanagedType.LPArray)]<br>&nbsp;&nbsp;&nbsp;&nbsp;&nbsp;&nbsp;&nbsp; public ConnectionData[] GetConnectionRawData(ConnectionType i_connectionType)<br>&nbsp;&nbsp;&nbsp;&nbsp;&nbsp;&nbsp;&nbsp; {<br>&nbsp;&nbsp;&nbsp;&nbsp;&nbsp;&nbsp;&nbsp;&nbsp;&nbsp;&nbsp;&nbsp; try<br>&nbsp;&nbsp;&nbsp;&nbsp;&nbsp;&nbsp;&nbsp;&nbsp;&nbsp;&nbsp;&nbsp; {<br>&nbsp;&nbsp;&nbsp;&nbsp;&nbsp;&nbsp;&nbsp;&nbsp;&nbsp;&nbsp;&nbsp;&nbsp;&nbsp;&nbsp;&nbsp; ConnectionData[] connectionData = _internalWeb.GetConnectionRawData(i_connectionType);<br>&nbsp;&nbsp;&nbsp;&nbsp;&nbsp;&nbsp;&nbsp;&nbsp;&nbsp;&nbsp;&nbsp;&nbsp;&nbsp;&nbsp;&nbsp; return connectionData;<br>&nbsp;&nbsp;&nbsp;&nbsp;&nbsp;&nbsp;&nbsp;&nbsp;&nbsp;&nbsp;&nbsp; }<br>&nbsp;&nbsp;&nbsp;&nbsp;&nbsp;&nbsp;&nbsp;&nbsp;&nbsp;&nbsp;&nbsp; catch (Exception ex)<br>&nbsp;&nbsp;&nbsp;&nbsp;&nbsp;&nbsp;&nbsp;&nbsp;&nbsp;&nbsp;&nbsp; {<br>&nbsp;&nbsp;&nbsp;&nbsp;&nbsp;&nbsp;&nbsp;&nbsp;&nbsp;&nbsp;&nbsp;&nbsp;&nbsp;&nbsp;&nbsp; ErrorMessage = string.Format(&quot;Failed to get All Connection data from Configuration Service. Attempting top get from File. {0}&quot;, ex.Message);<br>&nbsp;&nbsp;&nbsp;&nbsp;&nbsp;&nbsp;&nbsp;&nbsp;&nbsp;&nbsp;&nbsp;&nbsp;&nbsp;&nbsp;&nbsp; return new ConnectionData[] {};<br>&nbsp;&nbsp;&nbsp;&nbsp;&nbsp;&nbsp;&nbsp;&nbsp;&nbsp;&nbsp;&nbsp; }</p>\r\n<p>&nbsp;&nbsp;&nbsp;&nbsp;&nbsp;&nbsp;&nbsp; }</p>",
    "PostedDate": "2010-01-04T09:34:23.897-08:00",
    "UserRole": null,
    "MarkedAsAnswerDate": null
  }
]